    { 
        "QuestionPool" :
        [
        
        {   
            "question": "Who was the legendary Benedictine monk who invented champagne?",
            "right_answer": "a",
            "answers": { 
                "a": "Dom Perignon",
                "b": "Brandley James",
                "c": "Alice Cooper",
                "d": "Maria Alisson"
            }
        }, 

        {   
            "question": "Name the largest freshwater lake in the world?",
            "right_answer": "c",
            "answers": { 
                "a": "Lake Kerkini",
                "b": "Caspian sea",
                "c": "Lake Superior",
                "d": "Lake Victoria"
            }
        },

        {   
            "question": "Where would you find the Sea of Tranquility?",
            "right_answer": "d",
            "answers": {
                "a": "In Asia",
                "b": "The Earth",
                "c": "The Mars",
                "d": "The Moon"
            } 
        },

        {   
            "question": "What is someone who shoes horses called?",
            "right_answer": "a",
            "answers": {
                "a": "A farrier",
                "b": "A human",
                "c": "A painter",
                "d": "A farmer"
            } 
        },

        {   
            "question": "What kind of weapon is a falchion?",
            "right_answer": "d",
            "answers": {
                "a": "A BB Gun",
                "b": "A Fire Gun",
                "c": "A Rpg",
                "d": "A sword"
            } 
        },
        
        {   
            "question": "Name the seventh planet from the sun.",
            "right_answer": "c",
            "answers": {
                "a": "Zeus",
                "b": "Mars",
                "c": "Uranus",
                "d": "Aphrodite"
            } 
        }

    ] 
} 